toxicity/__init__.py
toxicity/final_model.py
toxicity/navecWeights.tar
toxicity/navec_vectorizer_layer.py
toxicity/dev/__init__.py
toxicity/dev/constants/__init__.py
toxicity/dev/constants/aliases.py
toxicity/dev/constants/default_hyperparameters.py
toxicity/dev/constants/graphs_style_params.py
toxicity/dev/constants/repo_paths.py
toxicity/dev/utils/__init__.py
toxicity/dev/utils/evaluate_model.py
toxicity/dev/utils/get_3d_quartile_words_count.py
toxicity/dev/utils/imbalanced_data_utils.py
toxicity/dev/utils/load_cleaned_russian_text_data.py
toxicity/dev/utils/pad_words_arr.py
toxicity/dev/utils/save_tf_model.py
toxicity/dev/utils/show_tf_model_summary.py
toxicity/dev/utils/tf_early_stopping.py
toxicity/dev/utils/translate_texts.py
toxicity/dev/utils/vectorize_sentence.py
toxicity/textPreprocessing/__init__.py
toxicity/textPreprocessing/preprocess_text.py
toxicity/textPreprocessing/text_utils/__init__.py
toxicity/textPreprocessing/text_utils/lemmatize.py
toxicity/textPreprocessing/text_utils/remove_numbers.py
toxicity/textPreprocessing/text_utils/remove_punctuation.py
toxicity/textPreprocessing/text_utils/remove_redundant_whitespace_chars.py
toxicity/weightedCNN_NavecWordEmbeddings/.DS_Store
toxicity/weightedCNN_NavecWordEmbeddings/saved_model.pb
toxicity/weightedCNN_NavecWordEmbeddings/variables/variables.data-00000-of-00001
toxicity/weightedCNN_NavecWordEmbeddings/variables/variables.index
toxicity-0.27.dist-info/METADATA
toxicity-0.27.dist-info/WHEEL
toxicity-0.27.dist-info/top_level.txt
toxicity-0.27.dist-info/RECORD
