Metadata-Version: 2.1
Name: toxicity
Version: 0.27
Summary: Deep learning classifier of russian toxic comments
Home-page: https://github.com/nsbarsukov/toxic-comments-detector
Author: Barsukov Nikita
Author-email: nikita.s.barsukov@gmail.com
License: MIT
Download-URL: https://github.com/nsbarsukov/toxic-comments-detector/archive/refs/tags/0.1.tar.gz
Keywords: toxic,comments,tensorflow,classifier
Platform: UNKNOWN
Classifier: Development Status :: 4 - Beta
Classifier: Intended Audience :: Developers
Classifier: Topic :: Software Development :: Build Tools
Classifier: License :: OSI Approved :: MIT License
Classifier: Programming Language :: Python :: 3
Requires-Dist: tensorflow
Requires-Dist: numpy
Requires-Dist: navec
